mercados/__init__.py
mercados/__main__.py
mercados/b3.py
mercados/bcb.py
mercados/choices.py
mercados/cvm.py
mercados/document.py
mercados/fundosnet.py
mercados/utils.py
mercados-0.2.0.dist-info/LICENSE
mercados-0.2.0.dist-info/METADATA
mercados-0.2.0.dist-info/WHEEL
mercados-0.2.0.dist-info/top_level.txt
mercados-0.2.0.dist-info/RECORD
