Metadata-Version: 2.1
Name: mercados
Version: 0.2.0
Summary: Scrapers para acessar dados do mercado financeiro brasileiro de diversos órgãos (CVM, BCB, B3), como Selic, CDI, IPCA, cadastro de fundos, CRAs, CRIs, debêntures, negociação bolsa e balcão etc.
Home-page: https://github.com/PythonicCafe/mercados/
Author: Álvaro Justen
Author-email: alvarojusten@gmail.com
License: GNU Lesser General Public License v3 (LGPLv3)
Keywords: finance market data CVM BCB B3 FII FI-Infra FI-Agro FIP Selic CDI IPCA IGP-M
Classifier: Intended Audience :: Developers
Classifier: License :: OSI Approved :: GNU Lesser General Public License v3 (LGPLv3)
Classifier: Operating System :: OS Independent
Classifier: Programming Language :: Python
Classifier: Programming Language :: Python :: 3
Classifier: Programming Language :: Python :: 3 :: Only
Classifier: Programming Language :: Python :: 3.8
Requires-Python: >=3.7
License-File: LICENSE
Requires-Dist: lxml
Requires-Dist: requests
Requires-Dist: xmltodict
